plait/__init__.py
plait/containers.py
plait/errors.py
plait/functional.py
plait/graph.py
plait/module.py
plait/parameter.py
plait/py.typed
plait/types.py
plait/values.py
plait/clients/__init__.py
plait/clients/base.py
plait/clients/openai.py
plait/execution/__init__.py
plait/execution/checkpoint.py
plait/execution/context.py
plait/execution/executor.py
plait/execution/scheduler.py
plait/execution/state.py
plait/execution/types.py
plait/optimization/__init__.py
plait/optimization/backward.py
plait/optimization/feedback.py
plait/optimization/loss.py
plait/optimization/optimizer.py
plait/optimization/record.py
plait/profiling/__init__.py
plait/profiling/profiler.py
plait/resources/__init__.py
plait/resources/config.py
plait/resources/manager.py
plait/resources/metrics.py
plait/resources/rate_limit.py
plait/tracing/__init__.py
plait/tracing/context.py
plait/tracing/tracer.py
pyplait-2026.1.1.dist-info/METADATA
pyplait-2026.1.1.dist-info/WHEEL
pyplait-2026.1.1.dist-info/licenses/LICENSE
pyplait-2026.1.1.dist-info/RECORD
