Metadata-Version: 2.4
Name: pyplait
Version: 2026.1.1
Summary: A PyTorch-inspired framework for LLM inference pipelines
License-File: LICENSE
Requires-Python: >=3.13
Requires-Dist: datasets>=3.0.0
Requires-Dist: openai>=2.14.0
Requires-Dist: rich>=13.0.0
